aliyunsdkaimath/__init__.py
aliyunsdkaimath/request/__init__.py
aliyunsdkaimath/request/v20241114/ChatMessageRequest.py
aliyunsdkaimath/request/v20241114/CreateConversationRequest.py
aliyunsdkaimath/request/v20241114/CreateRelatedConversationRequest.py
aliyunsdkaimath/request/v20241114/GenAnalysisRequest.py
aliyunsdkaimath/request/v20241114/GenStepRequest.py
aliyunsdkaimath/request/v20241114/GlobalConfirmRequest.py
aliyunsdkaimath/request/v20241114/UpdateAnalysisRequest.py
aliyunsdkaimath/request/v20241114/UpdateStepRequest.py
aliyunsdkaimath/request/v20241114/__init__.py
aliyun_python_sdk_aimath-1.0.1.dist-info/LICENSE
aliyun_python_sdk_aimath-1.0.1.dist-info/METADATA
aliyun_python_sdk_aimath-1.0.1.dist-info/WHEEL
aliyun_python_sdk_aimath-1.0.1.dist-info/top_level.txt
aliyun_python_sdk_aimath-1.0.1.dist-info/RECORD
